mypackage_himza_itcollege_lviv_ua/__init__.py
mypackage_himza_itcollege_lviv_ua/example.py
mypackage_himza_itcollege_lviv_ua-0.0.2.dist-info/LICENSE
mypackage_himza_itcollege_lviv_ua-0.0.2.dist-info/METADATA
mypackage_himza_itcollege_lviv_ua-0.0.2.dist-info/WHEEL
mypackage_himza_itcollege_lviv_ua-0.0.2.dist-info/top_level.txt
mypackage_himza_itcollege_lviv_ua-0.0.2.dist-info/RECORD
