Metadata-Version: 2.1
Name: mypackage-himza-itcollege-lviv-ua
Version: 0.0.2
Summary: Module for creating an email address
Home-page: https://github.com/pypa/sampleproject
Author: Dmytro Himza
Author-email: dhimza2020@itcollege.lviv.ua
Project-URL: Bug Tracker, https://github.com/pypa/sampleproject/issues
Classifier: Programming Language :: Python :: 3
Classifier: License :: OSI Approved :: MIT License
Classifier: Operating System :: OS Independent
Requires-Python: >=3.6
License-File: LICENSE
